alkh/__init__.py
alkh/analyze_call_graph.py
alkh/app.py
alkh/app_core.py
alkh/dump_data.py
alkh/logic_core.py
alkh/assets/__init__.py
alkh/assets/css/__init__.py
alkh/assets/css/prism-line-highlight.min.css
alkh/assets/css/prism-line-numbers.min.css
alkh/assets/css/prism-twilight.min.css
alkh/assets/scripts/__init__.py
alkh/assets/scripts/prism-autoloader.min.js
alkh/assets/scripts/prism-line-highlight.min.js
alkh/assets/scripts/prism-line-numbers.min.js
alkh/assets/scripts/prism-python.js
alkh/assets/scripts/prism-python.min.js
alkh/assets/scripts/prism.min.js
alkh/utils/__init__.py
alkh/utils/code_range_utils.py
alkh/utils/print_utils.py
notebooks/__init__.py
notebooks/play.py
notebooks/play2.py
notebooks/play3.py
tests/__init__.py
tests/analyze_test.py
tests/dump_data_test.py
tests/logic_core_test.py
tests/play.py
tests/play_imports.py
alkh-0.5.0.dist-info/LICENSE
alkh-0.5.0.dist-info/METADATA
alkh-0.5.0.dist-info/WHEEL
alkh-0.5.0.dist-info/top_level.txt
alkh-0.5.0.dist-info/RECORD
