Metadata-Version: 2.1
Name: alkh
Version: 0.5.0
Summary: algorithmic python debugging
Home-page: https://github.com/erez-aharonov/alkh
Author: Erez Aharonov
Author-email: ahar.erez@gmail.com
License: Apache License 2.0
Classifier: License :: OSI Approved :: Apache Software License
Classifier: Programming Language :: Python :: 3
Classifier: Programming Language :: Python :: 3.7
Classifier: Programming Language :: Python :: 3.8
Classifier: Programming Language :: Python :: 3.9
Classifier: Programming Language :: Python :: 3.10
Requires-Python: >=3.7.2
License-File: LICENSE
Requires-Dist: numpy (>=1.16.6)
Requires-Dist: pandas (>=0.25.0)
Requires-Dist: nbformat (>=5.1.3)
Requires-Dist: streamlit (>=1.12.0)
Requires-Dist: libcst (>=0.4.7)
Requires-Dist: networkx (>=2.5.1)
